Metadata-Version: 1.0
Name: defer
Version: 1.0
Summary: Simple framework for asynchronous programming
Home-page: http://launchpad.net/python-defer
Author: Sebastian Heinlein
Author-email: devel@glatzor.de
License: GNU GPL
Keywords: async defer dbus asynchronous
Platform: posix
Classifier: Development Status :: 5 - Production/Stable
Classifier: License :: OSI Approved :: GNU General Public License (GPL)
Classifier: Programming Language :: Python
Classifier: Topic :: Software Development :: Libraries :: Python Modules
